[
    {
        "title": "Vorlage Hinzuf\u00fcgen",
        "url": "https://stevenkellner.github.io/StrafenSupport/ReasonActions/AddReason",
        "tags": [
            "reason1"
        ]
    },
    {
        "title": "Vorlage L\u00f6schen",
        "url": "https://stevenkellner.github.io/StrafenSupport/ReasonActions/DeleteReason",
        "tags": [
            "reason3"
        ]
    },
    {
        "title": "Abmelden Anderer Erzwingen",
        "url": "https://stevenkellner.github.io/StrafenSupport/Settings/ForceSignOutSettings",
        "tags": [
            "settings3"
        ]
    },
    {
        "title": "Allgemeines",
        "url": "https://stevenkellner.github.io/StrafenSupport/General",
        "tags": [
            "general"
        ]
    },
    {
        "title": "Allgemeine Einstellungen",
        "url": "https://stevenkellner.github.io/StrafenSupport/Settings/GeneralSettings",
        "tags": [
            "settings"
        ]
    },
    {
        "title": "Verzugszinsen",
        "url": "https://stevenkellner.github.io/StrafenSupport/Settings/LatePaymentInterestSettings",
        "tags": [
            "settings1"
        ]
    },
    {
        "title": "Anmelden / Registrieren",
        "url": "https://stevenkellner.github.io/StrafenSupport/LogIn-SignIn",
        "tags": [
            "logIn-signIn"
        ]
    },
    {
        "title": "Strafen Teilen",
        "url": "https://stevenkellner.github.io/StrafenSupport/Settings/ShareFinesSettings",
        "tags": [
            "settings2"
        ]
    },
    {
        "title": "Vorlage \u00c4ndern",
        "url": "https://stevenkellner.github.io/StrafenSupport/ReasonActions/UpdateReason",
        "tags": [
            "reason2"
        ]
    }
]